{
  "flower": "tag:forge:storage_blocks/copper",
  "maxTimeInHive": 2400,
  "traits": ["nether"],
  "lore": "Just because there's tarnish on the copper,\ndoesn't mean there's not a shine beneath.",
  "loreColor": "#D28868",
  "hasHoneycomb": true,
  "baseLayerTexture": "ores/copper_bee",
  "ColorData": {
    "honeycombColor": "#D28868",
    "modelType": "DEFAULT"
  },
  "CentrifugeData": {
    "hasCentrifugeOutput": true,
    "mainOutput": "thermal:copper_ore",
    "mainOutputWeight": 0.50,
    "secondaryOutput": "thermal:copper_ingot",
    "secondaryOutputWeight": 0.01
  },
  "BreedData": {
    "isBreedable": true,
    "parent1": "Quartz",
    "parent2": "Stony",
    "breedChance": 0.75,
    "feedItem": "tag:forge:storage_blocks/copper",
    "feedAmount": 5
  },
  "TraitData": {
    "hasTraits": true
  }
}
